{
	"name": "pl_DQ_reconcile_run_all",
	"properties": {
		"activities": [
			{
				"name": "lkp_Get_All_Recon_Rules",
				"type": "Lookup",
				"dependsOn": [],
				"policy": {
					"timeout": "7.00:00:00",
					"retry": 0,
					"retryIntervalInSeconds": 30,
					"secureOutput": false,
					"secureInput": false
				},
				"userProperties": [],
				"typeProperties": {
					"source": {
						"type": "AzureTableSource",
						"azureTableSourceIgnoreTableNotFound": false
					},
					"dataset": {
						"referenceName": "ds_tbl_DQRuleReconList",
						"type": "DatasetReference"
					},
					"firstRowOnly": false
				}
			},
			{
				"name": "ForEachRule",
				"type": "ForEach",
				"dependsOn": [
					{
						"activity": "lkp_Get_All_Recon_Rules",
						"dependencyConditions": [
							"Succeeded"
						]
					}
				],
				"userProperties": [],
				"typeProperties": {
					"items": {
						"value": "@activity('lkp_Get_All_Recon_Rules').output.value",
						"type": "Expression"
					},
					"isSequential": false,
					"batchCount": 10,
					"activities": [
						{
							"name": "Execute Recon Rule",
							"type": "ExecutePipeline",
							"dependsOn": [],
							"userProperties": [],
							"typeProperties": {
								"pipeline": {
									"referenceName": "pl_DQ_reconcile_run",
									"type": "PipelineReference"
								},
								"waitOnCompletion": true,
								"parameters": {
									"RuleId": {
										"value": "@item().RuleId",
										"type": "Expression"
									}
								}
							}
						}
					]
				}
			},
			{
				"name": "Update DQReconResults",
				"type": "DatabricksNotebook",
				"dependsOn": [
					{
						"activity": "ForEachRule",
						"dependencyConditions": [
							"Completed"
						]
					}
				],
				"policy": {
					"timeout": "7.00:00:00",
					"retry": 0,
					"retryIntervalInSeconds": 30,
					"secureOutput": false,
					"secureInput": false
				},
				"userProperties": [],
				"typeProperties": {
					"notebookPath": "/DQ/DQReconResults_Refresh"
				},
				"linkedServiceName": {
					"referenceName": "ls_audi_databricks_v8x",
					"type": "LinkedServiceReference"
				}
			}
		],
		"folder": {
			"name": "DQ"
		},
		"annotations": [],
		"lastPublishTime": "2021-05-20T13:15:06Z"
	},
	"type": "Microsoft.DataFactory/factories/pipelines"
}