{
	"name": "trigger_stream_rogers_vod_fact_",
	"properties": {
		"annotations": [],
		"runtimeState": "Stopped",
		"pipeline": {
			"pipelineReference": {
				"referenceName": "pl_onprem_adls_delta_audi",
				"type": "PipelineReference"
			},
			"parameters": {
				"windowStart": "@{trigger().outputs.windowStartTime}",
				"windowEnd": "@{trigger().outputs.windowEndTime}",
				"schemaname": "mbuadl_agg_nonpi",
				"tablename": "stream_rogers_vod_fact"
			}
		},
		"type": "TumblingWindowTrigger",
		"typeProperties": {
			"frequency": "Hour",
			"interval": 24,
			"startTime": "2021-02-11T21:00:00Z",
			"delay": "00:00:00",
			"maxConcurrency": 50,
			"retryPolicy": {
				"intervalInSeconds": 30
			},
			"dependsOn": []
		}
	}
}